password_gl/__init__.py
password_gl/generator.py
password_gl-1.0.2.dist-info/licenses/LICENSE
password_gl-1.0.2.dist-info/METADATA
password_gl-1.0.2.dist-info/WHEEL
password_gl-1.0.2.dist-info/entry_points.txt
password_gl-1.0.2.dist-info/top_level.txt
password_gl-1.0.2.dist-info/RECORD
