Metadata-Version: 2.4
Name: password-gl
Version: 1.0.2
Summary: パスワードを生成するコマンドラインツール
Author: Lapius7bot Technology Co.
Author-email: contact-us@lapius7.com
License: MIT
Project-URL: Source, https://github.com/Lapius7/pip.password-gl
Project-URL: Bug Tracker, https://github.com/Lapius7/pip.password-gl/issues
License-File: LICENSE
Dynamic: author
Dynamic: author-email
Dynamic: description
Dynamic: description-content-type
Dynamic: license
Dynamic: license-file
Dynamic: project-url
Dynamic: summary
